cachepot/__init__.py
cachepot/app.py
cachepot/constants.py
cachepot/encoders.py
cachepot/py.typed
cachepot/routing.py
cachepot/storages/__init__.py
cachepot/storages/abstract.py
cachepot/storages/dummy.py
cachepot/storages/redis.py
cachepot/utils.py
fastapi_cachepot-0.1.0.dist-info/LICENSE
fastapi_cachepot-0.1.0.dist-info/METADATA
fastapi_cachepot-0.1.0.dist-info/WHEEL
fastapi_cachepot-0.1.0.dist-info/RECORD
