Metadata-Version: 2.1
Name: fastapi-cachepot
Version: 0.1.0
Summary: The FastAPI cache the way it should be.
Author: Aleksei Kotenko
Author-email: alexey+github@kotenko.me
Requires-Python: >=3.9,<4.0
Classifier: Programming Language :: Python :: 3
Classifier: Programming Language :: Python :: 3.9
Classifier: Programming Language :: Python :: 3.10
Classifier: Programming Language :: Python :: 3.11
Classifier: Programming Language :: Python :: 3.12
Requires-Dist: fastapi (>=0.106.0)
Requires-Dist: pydantic (>=2.0,<3.0)
Requires-Dist: redis (>=4.0.0,<5.0.0)
